cyan/__init__.py
cyan/bot.py
cyan/color.py
cyan/constant.py
cyan/event/__init__.py
cyan/event/_connection.py
cyan/event/channel.py
cyan/event/guild.py
cyan/event/member.py
cyan/event/message.py
cyan/exception.py
cyan/model/__init__.py
cyan/model/_dms.py
cyan/model/announcement.py
cyan/model/channel.py
cyan/model/guild.py
cyan/model/member.py
cyan/model/message/__init__.py
cyan/model/message/content.py
cyan/model/message/message.py
cyan/model/renovatable.py
cyan/model/role.py
cyan/model/schedule.py
cyan/model/user.py
cyan/py.typed
cyan/session.py
cyan/util/__init__.py
cyan/util/_enum.py
cyansdk-0.2.0.dist-info/LICENSE
cyansdk-0.2.0.dist-info/WHEEL
cyansdk-0.2.0.dist-info/METADATA
cyansdk-0.2.0.dist-info/RECORD
