Metadata-Version: 2.1
Name: cyansdk
Version: 0.2.0
Summary: A Python SDK for QQ Bot.
Home-page: https://gitlab.huajitech.net/huajitech/cyan
License: MIT
Keywords: bot,qq,qqbot
Author: Ricky8955555
Author-email: 397050061@qq.com
Requires-Python: >=3.7,<4.0
Classifier: License :: OSI Approved :: MIT License
Classifier: Programming Language :: Python :: 3
Classifier: Programming Language :: Python :: 3.10
Classifier: Programming Language :: Python :: 3.7
Classifier: Programming Language :: Python :: 3.8
Classifier: Programming Language :: Python :: 3.9
Requires-Dist: frozendict (>=2.2.0,<3.0.0)
Requires-Dist: httpx (>=0.21.3,<0.22.0)
Requires-Dist: websockets (>=10.1,<11.0)
Project-URL: Documentation, https://huajitech.proj.zone/cyan
Project-URL: Repository, https://gitlab.huajitech.net/huajitech/cyan
